flask_abc/__init__.py
flask_abc/commands.py
flask_abc-0.0.3.dist-info/METADATA
flask_abc-0.0.3.dist-info/WHEEL
flask_abc-0.0.3.dist-info/entry_points.txt
flask_abc-0.0.3.dist-info/RECORD
