Metadata-Version: 2.1
Name: flask-abc
Version: 0.0.3
Summary: 
Author: codeif
Author-email: me@codeif.com
Requires-Python: >=3.10,<4.0
Classifier: Programming Language :: Python :: 3
Classifier: Programming Language :: Python :: 3.10
Classifier: Programming Language :: Python :: 3.11
Requires-Dist: click (>=8.1.7,<9.0.0)
